{
  "sidebar_links": [
    {
      "title": "Tutorials",
      "links": [
        {
          "title": "Getting started with Habitat",
          "link": "/tutorials/getting-started-overview/",
          "sub_links": [
            {
              "title": "Basic concepts",
              "link": "/tutorials/getting-started-basic-concepts/"
            },
            {
              "title": "Set up your environment",
              "link": "/tutorials/getting-started-setup-environment/"
            },
            {
              "title": "Review the source files",
              "link": "/tutorials/getting-started-review-source-files/"
            },
            {
              "title": "Create your first plan",
              "link" : "/tutorials/getting-started-create-plan/"
            },
            {
              "title": "Add hooks to your plan",
              "link" : "/tutorials/getting-started-add-hooks/"
            },
            {
              "title": "Add configuration to your plan",
              "link" : "/tutorials/getting-started-configure-plan"
            },
            {
              "title": "Process your build",
              "link": "/tutorials/getting-started-process-build/"
            }
          ]
        }
      ]
    },
    {
      "title": "Quick Links",
      "links": [
        {
          "title": "Habitat docs",
          "link": "/docs"
        }
      ]
    }
  ]
}
